EpiLog/__init__.py
EpiLog/benchmark.py
EpiLog/manager.py
EpiLog/py.typed
EpiLog-1.1.2.dist-info/LICENSE
EpiLog-1.1.2.dist-info/METADATA
EpiLog-1.1.2.dist-info/WHEEL
EpiLog-1.1.2.dist-info/top_level.txt
EpiLog-1.1.2.dist-info/RECORD
