Metadata-Version: 2.1
Name: EpiLog
Version: 1.1.2
Summary: Simple No-Frills Logging Manager
Author-email: Jason C Del Rio <spillthetea917@gmail.com>
Maintainer-email: Jason C Del Rio <spillthetea917@gmail.com>
License: MIT License
Project-URL: homepage, https://github.com/Spill-Tea/EpiLog
Project-URL: issues, https://github.com/Spill-Tea/EpiLog/issues
Keywords: logging,benchmark
Classifier: Programming Language :: Python :: 3
Requires-Python: >=3.7
License-File: LICENSE
Provides-Extra: dev
Requires-Dist: EpiLog[doc,lint,test,type]; extra == "dev"
Requires-Dist: tox; extra == "dev"
Provides-Extra: doc
Requires-Dist: pdoc; extra == "doc"
Provides-Extra: test
Requires-Dist: pytest; extra == "test"
Requires-Dist: coverage; extra == "test"
Requires-Dist: pytest-xdist; extra == "test"
Provides-Extra: lint
Requires-Dist: pylint; extra == "lint"
Requires-Dist: ruff; extra == "lint"
Provides-Extra: type
Requires-Dist: mypy; extra == "type"
